pyflowsheet/__init__.py
pyflowsheet/bitmapcontext.py
pyflowsheet/blackbox.py
pyflowsheet/distillation.py
pyflowsheet/enums.py
pyflowsheet/figure.py
pyflowsheet/flowsheet.py
pyflowsheet/foreignObject.py
pyflowsheet/heatexchanger.py
pyflowsheet/mixer.py
pyflowsheet/pathfinder.py
pyflowsheet/port.py
pyflowsheet/pump.py
pyflowsheet/splitter.py
pyflowsheet/stream.py
pyflowsheet/streamflag.py
pyflowsheet/svgcontext.py
pyflowsheet/table.py
pyflowsheet/textelement.py
pyflowsheet/unitoperation.py
pyflowsheet/valve.py
pyflowsheet/vessel.py
pyflowsheet/annotations/__init__.py
pyflowsheet/annotations/figure.py
pyflowsheet/annotations/table.py
pyflowsheet/annotations/textelement.py
pyflowsheet/backends/__init__.py
pyflowsheet/backends/bitmapcontext.py
pyflowsheet/backends/foreignObject.py
pyflowsheet/backends/svgcontext.py
pyflowsheet/core/__init__.py
pyflowsheet/core/enums.py
pyflowsheet/core/flowsheet.py
pyflowsheet/core/pathfinder.py
pyflowsheet/core/port.py
pyflowsheet/core/stream.py
pyflowsheet/core/unitoperation.py
pyflowsheet/internals/__init__.py
pyflowsheet/internals/baffles.py
pyflowsheet/internals/baseinternal.py
pyflowsheet/internals/catalystBed.py
pyflowsheet/internals/discdonutbaffles.py
pyflowsheet/internals/dividingWall.py
pyflowsheet/internals/jacket.py
pyflowsheet/internals/liquidRing.py
pyflowsheet/internals/randomPacking.py
pyflowsheet/internals/reciprocating.py
pyflowsheet/internals/stirrer.py
pyflowsheet/internals/trays.py
pyflowsheet/internals/tubes.py
pyflowsheet/unitoperations/__init__.py
pyflowsheet/unitoperations/blackbox.py
pyflowsheet/unitoperations/compressor.py
pyflowsheet/unitoperations/distillation.py
pyflowsheet/unitoperations/heatexchanger.py
pyflowsheet/unitoperations/mixer.py
pyflowsheet/unitoperations/platehex.py
pyflowsheet/unitoperations/pump.py
pyflowsheet/unitoperations/splitter.py
pyflowsheet/unitoperations/streamflag.py
pyflowsheet/unitoperations/valve.py
pyflowsheet/unitoperations/vessel.py
pyflowsheet-0.2.2.dist-info/LICENSE
pyflowsheet-0.2.2.dist-info/METADATA
pyflowsheet-0.2.2.dist-info/WHEEL
pyflowsheet-0.2.2.dist-info/top_level.txt
pyflowsheet-0.2.2.dist-info/RECORD
