Metadata-Version: 2.1
Name: pyflowsheet
Version: 0.2.2
Summary: A Python library for creating process flow diagrams (PFD) for process engineering using SVG drawings.
Home-page: https://github.com/nukleon84/pyflowsheet
Author: Jochen Steimel
License: MIT License
Project-URL: Bug Reports, http://github.com/nukleon84/pyflowsheet/issues
Project-URL: Source, http://github.com/nukleon84/pyflowsheet/
Platform: OS Independent
Classifier: Development Status :: 3 - Alpha
Classifier: License :: OSI Approved :: MIT License
Classifier: Operating System :: OS Independent
Classifier: Programming Language :: Python :: 3
Classifier: Programming Language :: Python :: 3.7
Classifier: Programming Language :: Python :: 3.8
Classifier: Programming Language :: Python :: 3.9
Classifier: Programming Language :: Python :: Implementation :: CPython
Classifier: Programming Language :: Python :: Implementation :: PyPy
Classifier: Intended Audience :: Developers
Classifier: Topic :: Multimedia :: Graphics
Classifier: Topic :: Software Development :: Libraries :: Python Modules
Classifier: Topic :: Scientific/Engineering :: Chemistry
Provides: pyflowsheet
Requires-Python: >=3.7
Requires-Dist: svgwrite (>=1.4)
Requires-Dist: pathfinding (>=1.0.1)
Provides-Extra: plots
Requires-Dist: matplotlib ; extra == 'plots'
